ag_ui_adk/__init__.py
ag_ui_adk/adk_agent.py
ag_ui_adk/client_proxy_tool.py
ag_ui_adk/client_proxy_toolset.py
ag_ui_adk/config.py
ag_ui_adk/endpoint.py
ag_ui_adk/event_translator.py
ag_ui_adk/execution_state.py
ag_ui_adk/session_manager.py
ag_ui_adk/utils/__init__.py
ag_ui_adk/utils/converters.py
ag_ui_adk-0.4.0.dist-info/WHEEL
ag_ui_adk-0.4.0.dist-info/METADATA
ag_ui_adk-0.4.0.dist-info/RECORD
