Metadata-Version: 2.3
Name: ag-ui-adk
Version: 0.4.0
Author: Mark Fogle
Author-email: Mark Fogle <mark@contextable.com>
Requires-Dist: ag-ui-protocol>=0.1.10
Requires-Dist: aiohttp>=3.12.0
Requires-Dist: asyncio>=3.4.3
Requires-Dist: fastapi>=0.115.2
Requires-Dist: google-adk>=1.14.0
Requires-Dist: pydantic>=2.11.7
Requires-Dist: uvicorn>=0.35.0
Requires-Python: >=3.9, <3.14
